{
  "sources": [
    {
      "name": "Mailing List",
      "type": "lkml",
      "url": "https://lkml.org/",
      "active": true,
      "excludeAuthors": ["kernel test robot"],
      "lkmlDetailConcurrency": 12,
      "lkmlDetailTimeoutMs": 8000
    },
    {
      "name": "Mainline",
      "type": "git",
      "url": "https://git.kernel.org/pub/scm/linux/kernel/git/torvalds/linux.git",
      "active": true,
      "gitConfig": {
        "branch": "master",
        "sinceDays": 7,
        "maxCommits": 200,
        "localPath": "D:\\zouyipeng\\linux_mainline\\linux"
      }
    }
  ]
}
